{
    "Format": {
        "Type": "em5_order_info",
        "Version": "1"
    },
    "OrderInfo": {
        "core_lnz_o9_kdowa": {
            "Prefab": "em5/prefab/core_modded_prefabs/fw_2000_kdowa",
            "AvatarIcon": "kdowa",
            "SelectionIcon": "kdowa",
            "MiniMapIconType": "FirefighterVehicle",
            "LocalizedName": "core_lnz_kdowa",
            "UnitTags": "BF ControlStation ELW_A ELW_A ELW_B_reserve ELW_C_reserve_reserve",
            "OrderDepartment": "FireDepartment",
            "OrderCost": "10",
            "OrderSpeed": "10",
            "UnlockCost": "0",
            "NumberAvailable": "5",
            "PersonnelSpace": "2",
            "StartPersonnel": {
				"core_fagleder": "1",
				"core_pro_fm": "1",
				"core_pro_fm_pa": "0",
				"core_pro_fm_dekon": "0",
				"FirefighterABC": "0" // needed for dekon
            },
            "PassengerSpace": "0",
            "HelpPages": []
        }
    }
}
