{
    "Format": {
        "Type": "prefab",
        "Version": "2",
        "DifferenceToDefault": "true"
    },
    "Prototypes": {
        "1333733533668597750": {
            "qsf::MetadataComponent": {
                "Prefab": "18446744073709551615",
                "Name": "trailer_vu_commandable"
            },
            "qsf::TransformComponent": {
                "Scale": "1 0.9999997615814209 1"
            },
            "qsf::compositing::SkinnableMeshComponent": {
                "Mesh": "1395536731"
            },
            "qsf::LinkComponent": {
                "LocalPosition": "-8.9883804321289063e-05 -2.9995491786394268e-05 1.8692880868911743",
                "LocalRotation": "1 0 -5.4210115086623757e-20 2.8421712818535796e-14"
            },
            "qsf::BulletBoxCollisionComponent": {
                "CollisionMask": "3",
                "CollisionFilterGroup": "6144",
                "HalfExtents": "1.2799999713897705 2 4"
            },
            "em5::FireComponent": {
                "Active": "true",
                "FireMaterial": "civil_car_tanktruck",
                "SoftRadius": "10"
            }
        },
        "7595400499497000950": {
            "qsf::MetadataComponent": {
                "Prefab": "18446744073709551615",
                "Name": "trailer_krone_body000"
            },
            "qsf::TransformComponent": {
                "Position": "8.9883804321289063e-05 2.9995484510436654e-05 -1.8692880868911743",
                "Rotation": "0.99144136905670166 -1.7053028368747836e-13 -0.13055281341075897 1.9895199311788236e-13",
                "Scale": "1 0.9999997615814209 1"
            },
            "qsf::compositing::SkinnableMeshComponent": {
                "Mesh": "1395536733"
            },
            "qsf::LinkComponent": {
                "ParentId": "1333733533668597750",
                "LocalPosition": "8.9883804321289063e-05 2.9995491786394268e-05 -1.8692880868911743",
                "LocalRotation": "0.99144136905670166 -1.7053028368747836e-13 -0.13055281341075897 1.9895199311788236e-13"
            }
        },
        "15789326436652277751": {
            "qsf::MetadataComponent": {
                "Prefab": "18446744073709551615",
                "Name": "trailer_krone_wheel000"
            },
            "qsf::MeshComponent": {
                "Mesh": "1395536484"
            },
            "qsf::TransformComponent": {
                "Position": "-1.0579726696014404 0.46103814244270325 -2.2172350883483887",
                "Rotation": "0.99144136905670166 -1.7424081654501128e-13 -0.13055281341075897 2.2713046179088925e-13",
                "Scale": "-0.89710801839828491 0.89710783958435059 0.89710801839828491"
            },
            "qsf::LinkComponent": {
                "ParentId": "7595400499497000950",
                "LocalPosition": "-1.1120686531066895 0.46100828051567078 -0.062184631824493408",
                "LocalRotation": "1 0 -5.4210115086623757e-20 2.8421712818535796e-14",
                "LocalScale": "-0.89710801839828491 0.89710807800292969 0.89710801839828491"
            },
            "em5::WheelComponent": {
                "WheelType": "WHEELTYPE_BACK_LEFT"
            }
        },
        "16571393436693290999": {
            "qsf::MetadataComponent": {
                "Prefab": "18446744073709551615",
                "Name": "trailer_krone_wheel000"
            },
            "qsf::MeshComponent": {
                "Mesh": "1395536484"
            },
            "qsf::TransformComponent": {
                "Position": "0.91294634342193604 0.46103814244270325 -1.6889215707778931",
                "Rotation": "0.99144136905670166 -1.7424081654501128e-13 -0.13055281341075897 2.2713046179088925e-13",
                "Scale": "0.89710801839828491 0.89710783958435059 0.89710801839828491"
            },
            "qsf::LinkComponent": {
                "ParentId": "7595400499497000950",
                "LocalPosition": "0.92843055725097656 0.46100828051567078 -0.062093853950500488",
                "LocalRotation": "1 0 -5.4210115086623757e-20 2.8421712818535796e-14",
                "LocalScale": "0.89710801839828491 0.89710807800292969 0.89710801839828491"
            },
            "em5::WheelComponent": {
                "WheelType": "WHEELTYPE_BACK_RIGHT"
            }
        },
        "10199424563878027255": {
            "qsf::MetadataComponent": {
                "Prefab": "18446744073709551615",
                "Name": "trailer_krone_wheel000"
            },
            "qsf::MeshComponent": {
                "Mesh": "1395536484"
            },
            "qsf::TransformComponent": {
                "Position": "0.92854475975036621 0.46104148030281067 2.8325347900390625",
                "Rotation": "1 0 -5.4210115086623757e-20 2.8421712818535796e-14",
                "Scale": "0.89710801839828491 0.89710795879364014 0.89710801839828491"
            },
            "qsf::LinkComponent": {
                "ParentId": "1333733533668597750",
                "LocalPosition": "0.92854475975036621 0.46104159951210022 2.8325347900390625",
                "LocalRotation": "1 0 -5.4210115086623757e-20 2.8421712818535796e-14",
                "LocalScale": "0.89710801839828491 0.89710819721221924 0.89710801839828491"
            },
            "em5::WheelComponent": {
                "WheelType": "WHEELTYPE_BACK_RIGHT"
            }
        },
        "12483418129564164087": {
            "qsf::MetadataComponent": {
                "Prefab": "18446744073709551615",
                "Name": "wechselbruecke_lkw000"
            },
            "qsf::MeshComponent": {
                "Mesh": "1395536723"
            },
            "qsf::TransformComponent": {
                "Position": "-0.012679934501647949 1.2543244361877441 0.55749720335006714",
                "Rotation": "1 1.6459814560221275e-06 -2.5004152121255174e-05 -4.1183060434102359e-11"
            },
            "qsf::LinkComponent": {
                "ParentId": "1333733533668597750",
                "LocalPosition": "-0.012679934501647949 1.2543247938156128 0.55749720335006714",
                "LocalRotation": "1 1.6459814560221275e-06 -2.5004152121255174e-05 -4.1183060434102359e-11",
                "LocalScale": "1 1.0000002384185791 1"
            },
            "qsf::BulletBoxCollisionComponent": {
                "CollisionMask": "3",
                "CollisionFilterGroup": "6144",
                "HalfExtents": "1.3200000524520874 1.5099999904632568 3.8599998950958252"
            },
            "em5::RoadVehicleComponent": {
                "Resistances": "0.000000,0.000000",
                "SignalAudio": "18446744073709551615"
            }
        },
        "14103741906879504374": {
            "qsf::MetadataComponent": {
                "Prefab": "18446744073709551615",
                "Name": "trailer_krone_wheel000"
            },
            "qsf::MeshComponent": {
                "Mesh": "1395536484"
            },
            "qsf::TransformComponent": {
                "Position": "-1.1124496459960938 0.46104148030281067 2.8324465751647949",
                "Rotation": "1 0 -5.4210115086623757e-20 2.8421712818535796e-14",
                "Scale": "-0.89710801839828491 0.89710795879364014 0.89710801839828491"
            },
            "qsf::LinkComponent": {
                "ParentId": "1333733533668597750",
                "LocalPosition": "-1.1124496459960938 0.46104159951210022 2.8324465751647949",
                "LocalRotation": "1 0 -5.4210115086623757e-20 2.8421712818535796e-14",
                "LocalScale": "-0.89710801839828491 0.89710819721221924 0.89710801839828491"
            },
            "em5::WheelComponent": {
                "WheelType": "WHEELTYPE_BACK_LEFT"
            }
        }
    }
}
