{
    "Format": {
        "Type": "em5_order_info",
        "Version": "1"
    },
    "OrderInfo": {
        "oi_st9_gwl_o_98": {
            "Prefab": "em5/prefab/default/fw_2062_gwl",
            "AvatarIcon": "gwl1",
            "SelectionIcon": "gwl1",
            "MiniMapIconType": "FirefighterVehicle",
            "LocalizedName": "Logistikk O-9.8",
            "UnitTags": "BF GW_L GW-LOG SW_reserve",
            "OrderDepartment": "FireDepartment",
            "OrderCost": "10",
            "OrderSpeed": "10",
            "UnlockCost": "0",
            "NumberAvailable": "5",
            "PersonnelSpace": "2",
            "StartPersonnel": {
                "core_pro_sw": "2",
                "core_pro_sw_pa": "0",
                "core_pro_sw_dekon": "0",
                "FirefighterABC": "0"
            },
            "PassengerSpace": "0",
            "HelpPages": []
        }
    }
}
