{
    "Format": {
        "Type": "prefab",
        "Version": "2",
        "DifferenceToDefault": "true"
    },
    "Prototypes": {
        "2474507736": {
            "qsf::MetadataComponent": {
                "Prefab": "18446744073709551615",
                "Name": "logi_bygg"
            },
            "qsf::MeshComponent": {
                "Mesh": "2401992102"
            },
            "qsf::TransformComponent": "",
            "em5::ComplexFireComponent": {
                "FireEntities": [
                    "519263676777242754",
                    "18338008498732933251",
                    "3592231589298446466"
                ],
                "FireParticleEntities": [
                    "17177371695264056332",
                    "922770098980144136",
                    "13319172216438408203",
                    "11864348969445377035",
                    "14270194919142343692",
                    "15892109698373010445",
                    "11463245031688534813",
                    "12382300357232851744",
                    "15828614117344574240",
                    "2378783189353003809",
                    "553303431491634190",
                    "4251770486713645854",
                    "880626058805658632",
                    "17796636461006603274",
                    "3154635814098336543",
                    "6336867651680107293",
                    "6042675826561926154",
                    "6212689920835732494",
                    "4383624981973465887",
                    "17983247704776524813",
                    "6395006562381874183",
                    "879178882460056350",
                    "4328231410072568839",
                    "6370620498284397577"
                ]
            },
            "qsf::BulletTriangleMeshCollisionComponent": {
                "CollisionMask": "3",
                "CollisionFilterGroup": "6144"
            },
            "em5::BuildingComponent": {
                "IntactMesh": "18446744073709551615",
                "DamagedMesh": "18446744073709551615",
                "DestroyedMesh": "18446744073709551615",
                "CollapseDelay": "2",
                "IntactMaterial": "18446744073709551615",
                "DamageLevel1Material": "18446744073709551615",
                "ExplosionCenterWorldSpace": "0 0 0",
                "MainDoor": "7132056635803531817",
                "EventWindow": "13646151542721099919"
            },
            "qsf::LinkComponent": ""
        },
        "519263676777242754": {
            "qsf::LinkComponent": {
                "ParentLinkType": "HARD_LINK",
                "ParentId": "2474507736",
                "LocalPosition": "-238.85194396972656 4.4226689338684082 17.840545654296875",
                "LocalRotation": "0.9999619722366333 0 0.0087210480123758316 0",
                "LocalScale": "1.0936323404312134 1.0936323404312134 1.0936323404312134"
            },
            "qsf::MetadataComponent": {
                "Prefab": "8746",
                "Prototype": "16602931889622386204"
            },
            "qsf::TransformComponent": {
                "Position": "-238.85194396972656 4.4226689338684082 17.840545654296875",
                "Rotation": "0.9999619722366333 0 0.0087210480123758316 0",
                "Scale": "1.0936323404312134 1.0936323404312134 1.0936323404312134"
            },
            "em5::FireComponent": {
                "FireParticles": [
                    "14270194919142343692",
                    "15828614117344574240",
                    "2378783189353003809",
                    "4251770486713645854"
                ]
            }
        },
        "553303431491634190": {
            "qsf::MetadataComponent": {
                "Prefab": "8000001375",
                "Prototype": "3550738335218639445"
            },
            "qsf::ParticlesComponent": {
                "Active": "false",
                "EmitterEnabled": "false"
            },
            "qsf::TransformComponent": {
                "Position": "-258.93145751953125 2.7050552368164063 15.8682861328125",
                "Rotation": "1 0 0 0",
                "Scale": "0.5 0.5 0.5"
            },
            "em5::FireParticleOptionsComponent": {
                "FireLightEntity": "14714128171990533135"
            },
            "qsf::LinkComponent": {
                "ParentLinkType": "HARD_LINK",
                "ParentId": "2474507736",
                "LocalPosition": "-258.93145751953125 2.7050552368164063 15.8682861328125",
                "LocalRotation": "1 0 0 0",
                "LocalScale": "0.5 0.5 0.5"
            }
        },
        "14714128171990533135": {
            "qsf::MetadataComponent": {
                "Prefab": "8000001375",
                "Prototype": "11191939506507981397"
            },
            "qsf::TransformComponent": {
                "Position": "-258.10275268554688 2.603248119354248 15.80329704284668"
            },
            "qsf::LinkComponent": {
                "ParentId": "553303431491634190"
            }
        },
        "879178882460056350": {
            "qsf::MetadataComponent": {
                "Prefab": "8000001375",
                "Prototype": "3550738335218639445"
            },
            "qsf::ParticlesComponent": {
                "Active": "false",
                "EmitterEnabled": "false"
            },
            "qsf::TransformComponent": {
                "Position": "-215.22685241699219 5.9451136589050293 35.795196533203125",
                "Rotation": "0.7071068286895752 0 -0.7071068286895752 0",
                "Scale": "0.5 0.5 0.5"
            },
            "em5::FireParticleOptionsComponent": {
                "FireLightEntity": "9908952188956080926"
            },
            "qsf::LinkComponent": {
                "ParentLinkType": "HARD_LINK",
                "ParentId": "2474507736",
                "LocalPosition": "-215.22685241699219 5.9451136589050293 35.795196533203125",
                "LocalRotation": "0.7071068286895752 0 -0.7071068286895752 0",
                "LocalScale": "0.5 0.5 0.5"
            }
        },
        "9908952188956080926": {
            "qsf::MetadataComponent": {
                "Prefab": "8000001375",
                "Prototype": "11191939506507981397"
            },
            "qsf::TransformComponent": {
                "Position": "-215.161865234375 5.8433065414428711 36.623908996582031"
            },
            "qsf::LinkComponent": {
                "ParentId": "879178882460056350"
            }
        },
        "880626058805658632": {
            "qsf::MetadataComponent": {
                "Prefab": "8000001375",
                "Prototype": "3550738335218639445"
            },
            "qsf::ParticlesComponent": {
                "Active": "false",
                "EmitterEnabled": "false"
            },
            "qsf::TransformComponent": {
                "Position": "-234.04690551757813 2.7050552368164063 15.8682861328125",
                "Rotation": "1 0 0 0",
                "Scale": "0.5 0.5 0.5"
            },
            "em5::FireParticleOptionsComponent": {
                "FireLightEntity": "5315798619403600904"
            },
            "qsf::LinkComponent": {
                "ParentLinkType": "HARD_LINK",
                "ParentId": "2474507736",
                "LocalPosition": "-234.04690551757813 2.7050552368164063 15.8682861328125",
                "LocalRotation": "1 0 0 0",
                "LocalScale": "0.5 0.5 0.5"
            }
        },
        "5315798619403600904": {
            "qsf::MetadataComponent": {
                "Prefab": "8000001375",
                "Prototype": "11191939506507981397"
            },
            "qsf::TransformComponent": {
                "Position": "-233.21820068359375 2.603248119354248 15.80329704284668"
            },
            "qsf::LinkComponent": {
                "ParentId": "880626058805658632"
            }
        },
        "922770098980144136": {
            "qsf::MetadataComponent": {
                "Prefab": "8000001375",
                "Prototype": "3550738335218639445"
            },
            "qsf::ParticlesComponent": {
                "Active": "false",
                "EmitterEnabled": "false"
            },
            "qsf::TransformComponent": {
                "Position": "-226.76300048828125 9.72650146484375 18.370880126953125",
                "Rotation": "1 0 0 0",
                "Scale": "0.5 0.5 0.5"
            },
            "em5::FireParticleOptionsComponent": {
                "FireLightEntity": "4803741752107222025"
            },
            "qsf::LinkComponent": {
                "ParentLinkType": "HARD_LINK",
                "ParentId": "2474507736",
                "LocalPosition": "-226.76300048828125 9.72650146484375 18.370880126953125",
                "LocalRotation": "1 0 0 0",
                "LocalScale": "0.5 0.5 0.5"
            }
        },
        "4803741752107222025": {
            "qsf::MetadataComponent": {
                "Prefab": "8000001375",
                "Prototype": "11191939506507981397"
            },
            "qsf::TransformComponent": {
                "Position": "-225.93429565429688 9.62469482421875 18.305891036987305"
            },
            "qsf::LinkComponent": {
                "ParentId": "922770098980144136"
            }
        },
        "2378783189353003809": {
            "qsf::MetadataComponent": {
                "Prefab": "8000001375",
                "Prototype": "3550738335218639445"
            },
            "qsf::ParticlesComponent": {
                "Active": "false",
                "EmitterEnabled": "false"
            },
            "qsf::TransformComponent": {
                "Position": "-239.03585815429688 2.7050552368164063 15.8682861328125",
                "Rotation": "1 0 0 0",
                "Scale": "0.5 0.5 0.5"
            },
            "em5::FireParticleOptionsComponent": {
                "FireLightEntity": "8068066370518940449"
            },
            "qsf::LinkComponent": {
                "ParentLinkType": "HARD_LINK",
                "ParentId": "2474507736",
                "LocalPosition": "-239.03585815429688 2.7050552368164063 15.8682861328125",
                "LocalRotation": "1 0 0 0",
                "LocalScale": "0.5 0.5 0.5"
            }
        },
        "8068066370518940449": {
            "qsf::MetadataComponent": {
                "Prefab": "8000001375",
                "Prototype": "11191939506507981397"
            },
            "qsf::TransformComponent": {
                "Position": "-238.2071533203125 2.603248119354248 15.80329704284668"
            },
            "qsf::LinkComponent": {
                "ParentId": "2378783189353003809"
            }
        },
        "3154635814098336543": {
            "qsf::MetadataComponent": {
                "Prefab": "8000001375",
                "Prototype": "3550738335218639445"
            },
            "qsf::ParticlesComponent": {
                "Active": "false",
                "EmitterEnabled": "false"
            },
            "qsf::TransformComponent": {
                "Position": "-263.95440673828125 2.7050552368164063 15.8682861328125",
                "Rotation": "1 0 0 0",
                "Scale": "0.5 0.5 0.5"
            },
            "em5::FireParticleOptionsComponent": {
                "FireLightEntity": "12302408914645711647"
            },
            "qsf::LinkComponent": {
                "ParentLinkType": "HARD_LINK",
                "ParentId": "2474507736",
                "LocalPosition": "-263.95440673828125 2.7050552368164063 15.8682861328125",
                "LocalRotation": "1 0 0 0",
                "LocalScale": "0.5 0.5 0.5"
            }
        },
        "12302408914645711647": {
            "qsf::MetadataComponent": {
                "Prefab": "8000001375",
                "Prototype": "11191939506507981397"
            },
            "qsf::TransformComponent": {
                "Position": "-263.12570190429688 2.603248119354248 15.80329704284668"
            },
            "qsf::LinkComponent": {
                "ParentId": "3154635814098336543"
            }
        },
        "3592231589298446466": {
            "qsf::LinkComponent": {
                "ParentLinkType": "HARD_LINK",
                "ParentId": "2474507736",
                "LocalPosition": "-258.56134033203125 4.4226689338684082 17.840545654296875",
                "LocalRotation": "0.9999619722366333 0 0.0087210480123758316 0",
                "LocalScale": "1.0936323404312134 1.0936323404312134 1.0936323404312134"
            },
            "qsf::MetadataComponent": {
                "Prefab": "8746",
                "Prototype": "16602931889622386204"
            },
            "qsf::TransformComponent": {
                "Position": "-258.56134033203125 4.4226689338684082 17.840545654296875",
                "Rotation": "0.9999619722366333 0 0.0087210480123758316 0",
                "Scale": "1.0936323404312134 1.0936323404312134 1.0936323404312134"
            },
            "em5::FireComponent": {
                "FireParticles": [
                    "11864348969445377035",
                    "15892109698373010445",
                    "11463245031688534813",
                    "12382300357232851744",
                    "553303431491634190",
                    "3154635814098336543"
                ]
            }
        },
        "4251770486713645854": {
            "qsf::MetadataComponent": {
                "Prefab": "8000001375",
                "Prototype": "3550738335218639445"
            },
            "qsf::ParticlesComponent": {
                "Active": "false",
                "EmitterEnabled": "false"
            },
            "qsf::TransformComponent": {
                "Position": "-244.03256225585938 2.7050552368164063 15.8682861328125",
                "Rotation": "1 0 0 0",
                "Scale": "0.5 0.5 0.5"
            },
            "em5::FireParticleOptionsComponent": {
                "FireLightEntity": "17576633169360091934"
            },
            "qsf::LinkComponent": {
                "ParentLinkType": "HARD_LINK",
                "ParentId": "2474507736",
                "LocalPosition": "-244.03256225585938 2.7050552368164063 15.8682861328125",
                "LocalRotation": "1 0 0 0",
                "LocalScale": "0.5 0.5 0.5"
            }
        },
        "17576633169360091934": {
            "qsf::MetadataComponent": {
                "Prefab": "8000001375",
                "Prototype": "11191939506507981397"
            },
            "qsf::TransformComponent": {
                "Position": "-243.203857421875 2.603248119354248 15.80329704284668"
            },
            "qsf::LinkComponent": {
                "ParentId": "4251770486713645854"
            }
        },
        "4328231410072568839": {
            "qsf::MetadataComponent": {
                "Prefab": "8000001375",
                "Prototype": "3550738335218639445"
            },
            "qsf::ParticlesComponent": {
                "Active": "false",
                "EmitterEnabled": "false"
            },
            "qsf::TransformComponent": {
                "Position": "-215.22685241699219 9.72650146484375 21.65374755859375",
                "Rotation": "0.7071068286895752 0 -0.7071068286895752 0",
                "Scale": "0.5 0.5 0.5"
            },
            "em5::FireParticleOptionsComponent": {
                "FireLightEntity": "17648592825258886151"
            },
            "qsf::LinkComponent": {
                "ParentLinkType": "HARD_LINK",
                "ParentId": "2474507736",
                "LocalPosition": "-215.22685241699219 9.72650146484375 21.65374755859375",
                "LocalRotation": "0.7071068286895752 0 -0.7071068286895752 0",
                "LocalScale": "0.5 0.5 0.5"
            }
        },
        "17648592825258886151": {
            "qsf::MetadataComponent": {
                "Prefab": "8000001375",
                "Prototype": "11191939506507981397"
            },
            "qsf::TransformComponent": {
                "Position": "-215.161865234375 9.62469482421875 22.482460021972656"
            },
            "qsf::LinkComponent": {
                "ParentId": "4328231410072568839"
            }
        },
        "4383624981973465887": {
            "qsf::MetadataComponent": {
                "Prefab": "8000001375",
                "Prototype": "3550738335218639445"
            },
            "qsf::ParticlesComponent": {
                "Active": "false",
                "EmitterEnabled": "false"
            },
            "qsf::TransformComponent": {
                "Position": "-215.22685241699219 9.72650146484375 24.924102783203125",
                "Rotation": "0.7071068286895752 0 -0.7071068286895752 0",
                "Scale": "0.5 0.5 0.5"
            },
            "em5::FireParticleOptionsComponent": {
                "FireLightEntity": "17598121775505242912"
            },
            "qsf::LinkComponent": {
                "ParentLinkType": "HARD_LINK",
                "ParentId": "2474507736",
                "LocalPosition": "-215.22685241699219 9.72650146484375 24.924102783203125",
                "LocalRotation": "0.7071068286895752 0 -0.7071068286895752 0",
                "LocalScale": "0.5 0.5 0.5"
            }
        },
        "17598121775505242912": {
            "qsf::MetadataComponent": {
                "Prefab": "8000001375",
                "Prototype": "11191939506507981397"
            },
            "qsf::TransformComponent": {
                "Position": "-215.161865234375 9.62469482421875 25.752815246582031"
            },
            "qsf::LinkComponent": {
                "ParentId": "4383624981973465887"
            }
        },
        "6042675826561926154": {
            "qsf::MetadataComponent": {
                "Prefab": "8000001375",
                "Prototype": "3550738335218639445"
            },
            "qsf::ParticlesComponent": {
                "Active": "false",
                "EmitterEnabled": "false"
            },
            "qsf::TransformComponent": {
                "Position": "-215.22685241699219 9.72650146484375 35.795196533203125",
                "Rotation": "0.7071068286895752 0 -0.7071068286895752 0",
                "Scale": "0.5 0.5 0.5"
            },
            "em5::FireParticleOptionsComponent": {
                "FireLightEntity": "15035759654104744970"
            },
            "qsf::LinkComponent": {
                "ParentLinkType": "HARD_LINK",
                "ParentId": "2474507736",
                "LocalPosition": "-215.22685241699219 9.72650146484375 35.795196533203125",
                "LocalRotation": "0.7071068286895752 0 -0.7071068286895752 0",
                "LocalScale": "0.5 0.5 0.5"
            }
        },
        "15035759654104744970": {
            "qsf::MetadataComponent": {
                "Prefab": "8000001375",
                "Prototype": "11191939506507981397"
            },
            "qsf::TransformComponent": {
                "Position": "-215.161865234375 9.62469482421875 36.623908996582031"
            },
            "qsf::LinkComponent": {
                "ParentId": "6042675826561926154"
            }
        },
        "6212689920835732494": {
            "qsf::MetadataComponent": {
                "Prefab": "8000001375",
                "Prototype": "3550738335218639445"
            },
            "qsf::ParticlesComponent": {
                "Active": "false",
                "EmitterEnabled": "false"
            },
            "qsf::TransformComponent": {
                "Position": "-215.22685241699219 0.99748754501342773 35.8394775390625",
                "Rotation": "0.7071068286895752 0 -0.7071068286895752 0",
                "Scale": "0.5 0.5 0.5"
            },
            "em5::FireParticleOptionsComponent": {
                "FireLightEntity": "834029675143513102"
            },
            "qsf::LinkComponent": {
                "ParentLinkType": "HARD_LINK",
                "ParentId": "2474507736",
                "LocalPosition": "-215.22685241699219 0.99748754501342773 35.8394775390625",
                "LocalRotation": "0.7071068286895752 0 -0.7071068286895752 0",
                "LocalScale": "0.5 0.5 0.5"
            }
        },
        "834029675143513102": {
            "qsf::MetadataComponent": {
                "Prefab": "8000001375",
                "Prototype": "11191939506507981397"
            },
            "qsf::TransformComponent": {
                "Position": "-215.161865234375 0.89568042755126953 36.668190002441406"
            },
            "qsf::LinkComponent": {
                "ParentId": "6212689920835732494"
            }
        },
        "6336867651680107293": {
            "qsf::MetadataComponent": {
                "Prefab": "8000001375",
                "Prototype": "3550738335218639445"
            },
            "qsf::ParticlesComponent": {
                "Active": "false",
                "EmitterEnabled": "false"
            },
            "qsf::TransformComponent": {
                "Position": "-215.22685241699219 0.99748754501342773 28.94561767578125",
                "Rotation": "0.7071068286895752 0 -0.7071068286895752 0",
                "Scale": "0.5 0.5 0.5"
            },
            "em5::FireParticleOptionsComponent": {
                "FireLightEntity": "3880282697809951517"
            },
            "qsf::LinkComponent": {
                "ParentLinkType": "HARD_LINK",
                "ParentId": "2474507736",
                "LocalPosition": "-215.22685241699219 0.99748754501342773 28.94561767578125",
                "LocalRotation": "0.7071068286895752 0 -0.7071068286895752 0",
                "LocalScale": "0.5 0.5 0.5"
            }
        },
        "3880282697809951517": {
            "qsf::MetadataComponent": {
                "Prefab": "8000001375",
                "Prototype": "11191939506507981397"
            },
            "qsf::TransformComponent": {
                "Position": "-215.161865234375 0.89568042755126953 29.774330139160156"
            },
            "qsf::LinkComponent": {
                "ParentId": "6336867651680107293"
            }
        },
        "6370620498284397577": {
            "qsf::MetadataComponent": {
                "Prefab": "8000001375",
                "Prototype": "3550738335218639445"
            },
            "qsf::ParticlesComponent": {
                "Active": "false",
                "EmitterEnabled": "false"
            },
            "qsf::TransformComponent": {
                "Position": "-215.22685241699219 5.9451136589050293 28.23675537109375",
                "Rotation": "0.7071068286895752 0 -0.7071068286895752 0",
                "Scale": "0.5 0.5 0.5"
            },
            "em5::FireParticleOptionsComponent": {
                "FireLightEntity": "16897475711740167177"
            },
            "qsf::LinkComponent": {
                "ParentLinkType": "HARD_LINK",
                "ParentId": "2474507736",
                "LocalPosition": "-215.22685241699219 5.9451136589050293 28.23675537109375",
                "LocalRotation": "0.7071068286895752 0 -0.7071068286895752 0",
                "LocalScale": "0.5 0.5 0.5"
            }
        },
        "16897475711740167177": {
            "qsf::MetadataComponent": {
                "Prefab": "8000001375",
                "Prototype": "11191939506507981397"
            },
            "qsf::TransformComponent": {
                "Position": "-215.161865234375 5.8433065414428711 29.065467834472656"
            },
            "qsf::LinkComponent": {
                "ParentId": "6370620498284397577"
            }
        },
        "6395006562381874183": {
            "qsf::MetadataComponent": {
                "Prefab": "8000001375",
                "Prototype": "3550738335218639445"
            },
            "qsf::ParticlesComponent": {
                "Active": "false",
                "EmitterEnabled": "false"
            },
            "qsf::TransformComponent": {
                "Position": "-215.22685241699219 0.99748754501342773 32.60125732421875",
                "Rotation": "0.7071068286895752 0 -0.7071068286895752 0",
                "Scale": "0.5 0.5 0.5"
            },
            "em5::FireParticleOptionsComponent": {
                "FireLightEntity": "9287828385274283015"
            },
            "qsf::LinkComponent": {
                "ParentLinkType": "HARD_LINK",
                "ParentId": "2474507736",
                "LocalPosition": "-215.22685241699219 0.99748754501342773 32.60125732421875",
                "LocalRotation": "0.7071068286895752 0 -0.7071068286895752 0",
                "LocalScale": "0.5 0.5 0.5"
            }
        },
        "9287828385274283015": {
            "qsf::MetadataComponent": {
                "Prefab": "8000001375",
                "Prototype": "11191939506507981397"
            },
            "qsf::TransformComponent": {
                "Position": "-215.161865234375 0.89568042755126953 33.429969787597656"
            },
            "qsf::LinkComponent": {
                "ParentId": "6395006562381874183"
            }
        },
        "7132056635803531817": {
            "qsf::MetadataComponent": {
                "Prefab": "3940952995",
                "Prototype": "13959213405059048870",
                "Name": "door_main_entrance_entity0"
            },
            "qsf::TransformComponent": {
                "Position": "-240.13223266601563 0 41.211273193359375",
                "Rotation": "-4.3711388286737929e-08 0 1 0"
            },
            "qsf::LinkComponent": {
                "ParentLinkType": "HARD_LINK",
                "ParentId": "2474507736",
                "LocalPosition": "-240.13223266601563 0 41.211273193359375",
                "LocalRotation": "-4.3711388286737929e-08 0 1 0",
                "LocalScale": "1 1 1"
            }
        },
        "7190556139074803036": {
            "qsf::MetadataComponent": {
                "Prefab": "2401992143",
                "Prototype": "2076720420",
                "Name": "logi_bygg_vehicle_gates0"
            },
            "qsf::TransformComponent": {
                "Position": "0 0 0"
            },
            "qsf::LinkComponent": {
                "ParentLinkType": "HARD_LINK",
                "ParentId": "2474507736",
                "LocalPosition": "0 0 0",
                "LocalRotation": "1 0 0 0",
                "LocalScale": "1 1 1"
            }
        },
        "11463245031688534813": {
            "qsf::MetadataComponent": {
                "Prefab": "8000001375",
                "Prototype": "3550738335218639445"
            },
            "qsf::ParticlesComponent": {
                "Active": "false",
                "EmitterEnabled": "false"
            },
            "qsf::TransformComponent": {
                "Position": "-272.34420776367188 9.72650146484375 18.276824951171875",
                "Rotation": "1 0 0 0",
                "Scale": "0.5 0.5 0.5"
            },
            "em5::FireParticleOptionsComponent": {
                "FireLightEntity": "17457179997030480669"
            },
            "qsf::LinkComponent": {
                "ParentLinkType": "HARD_LINK",
                "ParentId": "2474507736",
                "LocalPosition": "-272.34420776367188 9.72650146484375 18.276824951171875",
                "LocalRotation": "1 0 0 0",
                "LocalScale": "0.5 0.5 0.5"
            }
        },
        "17457179997030480669": {
            "qsf::MetadataComponent": {
                "Prefab": "8000001375",
                "Prototype": "11191939506507981397"
            },
            "qsf::TransformComponent": {
                "Position": "-271.5155029296875 9.62469482421875 18.211835861206055"
            },
            "qsf::LinkComponent": {
                "ParentId": "11463245031688534813"
            }
        },
        "11864348969445377035": {
            "qsf::MetadataComponent": {
                "Prefab": "8000001375",
                "Prototype": "3550738335218639445"
            },
            "qsf::ParticlesComponent": {
                "Active": "false",
                "EmitterEnabled": "false"
            },
            "qsf::TransformComponent": {
                "Position": "-250.55949401855469 9.72650146484375 18.276824951171875",
                "Rotation": "1 0 0 0",
                "Scale": "0.5 0.5 0.5"
            },
            "em5::FireParticleOptionsComponent": {
                "FireLightEntity": "16576810781951149068"
            },
            "qsf::LinkComponent": {
                "ParentLinkType": "HARD_LINK",
                "ParentId": "2474507736",
                "LocalPosition": "-250.55949401855469 9.72650146484375 18.276824951171875",
                "LocalRotation": "1 0 0 0",
                "LocalScale": "0.5 0.5 0.5"
            }
        },
        "16576810781951149068": {
            "qsf::MetadataComponent": {
                "Prefab": "8000001375",
                "Prototype": "11191939506507981397"
            },
            "qsf::TransformComponent": {
                "Position": "-249.73078918457031 9.62469482421875 18.211835861206055"
            },
            "qsf::LinkComponent": {
                "ParentId": "11864348969445377035"
            }
        },
        "12001210726557523091": {
            "qsf::MetadataComponent": {
                "Prefab": "2401992105",
                "Prototype": "3575078654",
                "Name": "logi_bygg_extension0"
            },
            "qsf::TransformComponent": {
                "Position": "0 0 0"
            },
            "qsf::LinkComponent": {
                "ParentLinkType": "HARD_LINK",
                "ParentId": "2474507736",
                "LocalPosition": "0 0 0",
                "LocalRotation": "1 0 0 0",
                "LocalScale": "1 1 1"
            }
        },
        "12382300357232851744": {
            "qsf::MetadataComponent": {
                "Prefab": "8000001375",
                "Prototype": "3550738335218639445"
            },
            "qsf::ParticlesComponent": {
                "Active": "false",
                "EmitterEnabled": "false"
            },
            "qsf::TransformComponent": {
                "Position": "-266.89898681640625 9.72650146484375 18.276824951171875",
                "Rotation": "1 0 0 0",
                "Scale": "0.5 0.5 0.5"
            },
            "em5::FireParticleOptionsComponent": {
                "FireLightEntity": "15517320325159090977"
            },
            "qsf::LinkComponent": {
                "ParentLinkType": "HARD_LINK",
                "ParentId": "2474507736",
                "LocalPosition": "-266.89898681640625 9.72650146484375 18.276824951171875",
                "LocalRotation": "1 0 0 0",
                "LocalScale": "0.5 0.5 0.5"
            }
        },
        "15517320325159090977": {
            "qsf::MetadataComponent": {
                "Prefab": "8000001375",
                "Prototype": "11191939506507981397"
            },
            "qsf::TransformComponent": {
                "Position": "-266.07028198242188 9.62469482421875 18.211835861206055"
            },
            "qsf::LinkComponent": {
                "ParentId": "12382300357232851744"
            }
        },
        "13319172216438408203": {
            "qsf::MetadataComponent": {
                "Prefab": "8000001375",
                "Prototype": "3550738335218639445"
            },
            "qsf::ParticlesComponent": {
                "Active": "false",
                "EmitterEnabled": "false"
            },
            "qsf::TransformComponent": {
                "Position": "-220.44606018066406 9.72650146484375 18.370880126953125",
                "Rotation": "1 0 0 0",
                "Scale": "0.5 0.5 0.5"
            },
            "em5::FireParticleOptionsComponent": {
                "FireLightEntity": "9351351492748002315"
            },
            "qsf::LinkComponent": {
                "ParentLinkType": "HARD_LINK",
                "ParentId": "2474507736",
                "LocalPosition": "-220.44606018066406 9.72650146484375 18.370880126953125",
                "LocalRotation": "1 0 0 0",
                "LocalScale": "0.5 0.5 0.5"
            }
        },
        "9351351492748002315": {
            "qsf::MetadataComponent": {
                "Prefab": "8000001375",
                "Prototype": "11191939506507981397"
            },
            "qsf::TransformComponent": {
                "Position": "-219.61735534667969 9.62469482421875 18.305891036987305"
            },
            "qsf::LinkComponent": {
                "ParentId": "13319172216438408203"
            }
        },
        "13646151542721099919": {
            "qsf::MetadataComponent": {
                "Prefab": "3940953017",
                "Prototype": "3424980494350729134",
                "Name": "eventwindow_entity0"
            },
            "qsf::TransformComponent": {
                "Position": "-216.27685546875 11.972710609436035 40.30706787109375"
            },
            "qsf::LinkComponent": {
                "ParentLinkType": "HARD_LINK",
                "ParentId": "2474507736",
                "LocalPosition": "-216.27685546875 11.972710609436035 40.30706787109375",
                "LocalRotation": "1 0 0 0",
                "LocalScale": "1 1 1"
            }
        },
        "14270194919142343692": {
            "qsf::MetadataComponent": {
                "Prefab": "8000001375",
                "Prototype": "3550738335218639445"
            },
            "qsf::ParticlesComponent": {
                "Active": "false",
                "EmitterEnabled": "false"
            },
            "qsf::TransformComponent": {
                "Position": "-244.73277282714844 9.72650146484375 18.276824951171875",
                "Rotation": "1 0 0 0",
                "Scale": "0.5 0.5 0.5"
            },
            "em5::FireParticleOptionsComponent": {
                "FireLightEntity": "2689623767999595532"
            },
            "qsf::LinkComponent": {
                "ParentLinkType": "HARD_LINK",
                "ParentId": "2474507736",
                "LocalPosition": "-244.73277282714844 9.72650146484375 18.276824951171875",
                "LocalRotation": "1 0 0 0",
                "LocalScale": "0.5 0.5 0.5"
            }
        },
        "2689623767999595532": {
            "qsf::MetadataComponent": {
                "Prefab": "8000001375",
                "Prototype": "11191939506507981397"
            },
            "qsf::TransformComponent": {
                "Position": "-243.90406799316406 9.62469482421875 18.211835861206055"
            },
            "qsf::LinkComponent": {
                "ParentId": "14270194919142343692"
            }
        },
        "15828614117344574240": {
            "qsf::MetadataComponent": {
                "Prefab": "8000001375",
                "Prototype": "3550738335218639445"
            },
            "qsf::ParticlesComponent": {
                "Active": "false",
                "EmitterEnabled": "false"
            },
            "qsf::TransformComponent": {
                "Position": "-238.58201599121094 9.72650146484375 18.276824951171875",
                "Rotation": "1 0 0 0",
                "Scale": "0.5 0.5 0.5"
            },
            "em5::FireParticleOptionsComponent": {
                "FireLightEntity": "5792533671362591520"
            },
            "qsf::LinkComponent": {
                "ParentLinkType": "HARD_LINK",
                "ParentId": "2474507736",
                "LocalPosition": "-238.58201599121094 9.72650146484375 18.276824951171875",
                "LocalRotation": "1 0 0 0",
                "LocalScale": "0.5 0.5 0.5"
            }
        },
        "5792533671362591520": {
            "qsf::MetadataComponent": {
                "Prefab": "8000001375",
                "Prototype": "11191939506507981397"
            },
            "qsf::TransformComponent": {
                "Position": "-237.75331115722656 9.62469482421875 18.211835861206055"
            },
            "qsf::LinkComponent": {
                "ParentId": "15828614117344574240"
            }
        },
        "15892109698373010445": {
            "qsf::MetadataComponent": {
                "Prefab": "8000001375",
                "Prototype": "3550738335218639445"
            },
            "qsf::ParticlesComponent": {
                "Active": "false",
                "EmitterEnabled": "false"
            },
            "qsf::TransformComponent": {
                "Position": "-256.51077270507813 9.72650146484375 18.276824951171875",
                "Rotation": "1 0 0 0",
                "Scale": "0.5 0.5 0.5"
            },
            "em5::FireParticleOptionsComponent": {
                "FireLightEntity": "15727215939555443726"
            },
            "qsf::LinkComponent": {
                "ParentLinkType": "HARD_LINK",
                "ParentId": "2474507736",
                "LocalPosition": "-256.51077270507813 9.72650146484375 18.276824951171875",
                "LocalRotation": "1 0 0 0",
                "LocalScale": "0.5 0.5 0.5"
            }
        },
        "15727215939555443726": {
            "qsf::MetadataComponent": {
                "Prefab": "8000001375",
                "Prototype": "11191939506507981397"
            },
            "qsf::TransformComponent": {
                "Position": "-255.68206787109375 9.62469482421875 18.211835861206055"
            },
            "qsf::LinkComponent": {
                "ParentId": "15892109698373010445"
            }
        },
        "16287546869164383379": {
            "qsf::MetadataComponent": {
                "Prefab": "2401992117",
                "Prototype": "1347909851",
                "Name": "logi_bygg_ramp0"
            },
            "qsf::TransformComponent": {
                "Position": "0 0 0"
            },
            "qsf::LinkComponent": {
                "ParentLinkType": "HARD_LINK",
                "ParentId": "2474507736",
                "LocalPosition": "0 0 0",
                "LocalRotation": "1 0 0 0",
                "LocalScale": "1 1 1"
            }
        },
        "17177371695264056332": {
            "qsf::MetadataComponent": {
                "Prefab": "8000001375",
                "Prototype": "3550738335218639445"
            },
            "qsf::ParticlesComponent": {
                "Active": "false",
                "EmitterEnabled": "false"
            },
            "qsf::TransformComponent": {
                "Position": "-232.45420837402344 9.72650146484375 18.276824951171875",
                "Rotation": "1 0 0 0",
                "Scale": "0.5 0.5 0.5"
            },
            "em5::FireParticleOptionsComponent": {
                "FireLightEntity": "9473854658793456653"
            },
            "qsf::LinkComponent": {
                "ParentLinkType": "HARD_LINK",
                "ParentId": "2474507736",
                "LocalPosition": "-232.45420837402344 9.72650146484375 18.276824951171875",
                "LocalRotation": "1 0 0 0",
                "LocalScale": "0.5 0.5 0.5"
            }
        },
        "9473854658793456653": {
            "qsf::MetadataComponent": {
                "Prefab": "8000001375",
                "Prototype": "11191939506507981397"
            },
            "qsf::TransformComponent": {
                "Position": "-231.62550354003906 9.62469482421875 18.211835861206055"
            },
            "qsf::LinkComponent": {
                "ParentId": "17177371695264056332"
            }
        },
        "17796636461006603274": {
            "qsf::MetadataComponent": {
                "Prefab": "8000001375",
                "Prototype": "3550738335218639445"
            },
            "qsf::ParticlesComponent": {
                "Active": "false",
                "EmitterEnabled": "false"
            },
            "qsf::TransformComponent": {
                "Position": "-228.977783203125 2.7050552368164063 15.8682861328125",
                "Rotation": "1 0 0 0",
                "Scale": "0.5 0.5 0.5"
            },
            "em5::FireParticleOptionsComponent": {
                "FireLightEntity": "14235816454716933130"
            },
            "qsf::LinkComponent": {
                "ParentLinkType": "HARD_LINK",
                "ParentId": "2474507736",
                "LocalPosition": "-228.977783203125 2.7050552368164063 15.8682861328125",
                "LocalRotation": "1 0 0 0",
                "LocalScale": "0.5 0.5 0.5"
            }
        },
        "14235816454716933130": {
            "qsf::MetadataComponent": {
                "Prefab": "8000001375",
                "Prototype": "11191939506507981397"
            },
            "qsf::TransformComponent": {
                "Position": "-228.14907836914063 2.603248119354248 15.80329704284668"
            },
            "qsf::LinkComponent": {
                "ParentId": "17796636461006603274"
            }
        },
        "17983247704776524813": {
            "qsf::MetadataComponent": {
                "Prefab": "8000001375",
                "Prototype": "3550738335218639445"
            },
            "qsf::ParticlesComponent": {
                "Active": "false",
                "EmitterEnabled": "false"
            },
            "qsf::TransformComponent": {
                "Position": "-215.22685241699219 9.72650146484375 32.52484130859375",
                "Rotation": "0.7071068286895752 0 -0.7071068286895752 0",
                "Scale": "0.5 0.5 0.5"
            },
            "em5::FireParticleOptionsComponent": {
                "FireLightEntity": "8225848501013070861"
            },
            "qsf::LinkComponent": {
                "ParentLinkType": "HARD_LINK",
                "ParentId": "2474507736",
                "LocalPosition": "-215.22685241699219 9.72650146484375 32.52484130859375",
                "LocalRotation": "0.7071068286895752 0 -0.7071068286895752 0",
                "LocalScale": "0.5 0.5 0.5"
            }
        },
        "8225848501013070861": {
            "qsf::MetadataComponent": {
                "Prefab": "8000001375",
                "Prototype": "11191939506507981397"
            },
            "qsf::TransformComponent": {
                "Position": "-215.161865234375 9.62469482421875 33.353553771972656"
            },
            "qsf::LinkComponent": {
                "ParentId": "17983247704776524813"
            }
        },
        "18338008498732933251": {
            "qsf::LinkComponent": {
                "ParentLinkType": "HARD_LINK",
                "ParentId": "2474507736",
                "LocalPosition": "-233.43061828613281 4.4226689338684082 17.840545654296875",
                "LocalRotation": "0.9999619722366333 0 0.0087210480123758316 0",
                "LocalScale": "1.0936323404312134 1.0936323404312134 1.0936323404312134"
            },
            "qsf::MetadataComponent": {
                "Prefab": "8746",
                "Prototype": "16602931889622386204"
            },
            "qsf::TransformComponent": {
                "Position": "-233.43061828613281 4.4226689338684082 17.840545654296875",
                "Rotation": "0.9999619722366333 0 0.0087210480123758316 0",
                "Scale": "1.0936323404312134 1.0936323404312134 1.0936323404312134"
            },
            "em5::FireComponent": {
                "FireParticles": [
                    "17177371695264056332",
                    "922770098980144136",
                    "13319172216438408203",
                    "880626058805658632",
                    "17796636461006603274",
                    "6336867651680107293",
                    "6042675826561926154",
                    "6212689920835732494",
                    "4383624981973465887",
                    "17983247704776524813",
                    "6395006562381874183",
                    "879178882460056350",
                    "4328231410072568839",
                    "6370620498284397577"
                ]
            }
        }
    }
}
