{
    "Format": {
        "Type": "prefab",
        "Version": "2",
        "DifferenceToDefault": "true"
    },
    "Prototypes": {
        "3537955314538595921": {
            "qsf::MetadataComponent": {
                "Prefab": "18446744073709551615",
                "Name": "core_pro_sw_dekon",
                "Description": "firefighter",
                "Tags": "person;firefighter;dekon"
            },
            "qsf::TransformComponent": "",
            "qsf::MovableComponent": {
                "GroundSpeedCategory": "squad"
            },
            "qsf::ai::NavigationComponent": {
                "MoverType": "1",
                "MaxSpeed": "3.2999999523162842",
                "MaxTurningChange": "6",
                "BackwardSpeedFactor": "0.40000000596046448",
                "DesiredAcceleration": "5",
                "MainNavMapId": "1",
                "AvoidCollisionTypes": "20",
                "AvoidCollisionMeasures": "3",
                "CurveSmoothing": "0",
                "DistanceToKeepAhead": "0",
                "CollisionMask": "37",
                "PrioritySearch": "true",
                "AdditionalCollisionLookaheadDistance": "10"
            },
            "em5::HealthComponent": {
                "HealthEnergy": "1000",
                "MaximumHealthEnergy": "1000",
                "LifeEnergy": "1000",
                "MaximumLifeEnergy": "1000",
                "Immunities": "IMMUNITY_ILLNESS,IMMUNITY_CONTAMINATION_RADIOACTIVE,IMMUNITY_CONTAMINATION_CHEMICAL,IMMUNITY_CONTAMINATION_BIOLOGICAL,IMMUNITY_CONTAMINATION_PLAGUE",
                "Resistances": "1.000000,0.150000,0.250000"
            },
            "qsf::game::SelectableComponent": "",
            "em5::CommandableComponent": {
                "CommandArray": [
                    "avc::EnterDLK",
                    "em5::BreakBuildingDoorOpenCommand",
                    "em5::CoolWithExtinguisherCommand",
                    "em5::CutTreeCommand",
                    "em5::DecontaminatePersonCommand",
                    "em5::ExtinguishWithExtinguisherCommand",
                    "em5::MoveCommand",
                    "em5::PickupContaminatedPersonCommand",
                    "em5::RescuePersonFromBuildingCommand",
                    "em5::StartPullObjectCommand",
                    "em5::StopPullObjectCommand",
                    "evt::AdvancedBuildingEventEnterBuildingCommand",
                    "evt::ContaminationCloseValveCommand",
                    "evt::CutRoadVehicleCommand",
                    "evt::FireBridgeChangeStateCommand",
                    "evt::ModularEventCloseOilLeakCommand",
                    "evt::ModularEventCoverManholeCommand",
                    "evt::ModularEventDisconnectBatterieCommand",
                    "evt::ModularEventRemoveOilPuddleCommand",
                    "evt::ModularEventUseShovelCommand",
                    "evt::PumpWaterCommand",
                    "evt::InvestigateBMACommand",
                    "inventory::DropEquipmentCommand",
                    "inventory::GetAxeMenuCommand",
                    "inventory::GetChainSawMenuCommand",
                    "inventory::GetFireExtinguisherCommand",
                    "inventory::GetHoseCommand",
                    "inventory::GetManholeCoverBarrierMenuCommand",
                    "inventory::GetMedicBagCommand",
                    "inventory::GetOilSorberFluidMenuCommand",
                    "inventory::GetOilSorberPowderMenuCommand",
                    "inventory::GetRescueCutterMenuCommand",
                    "inventory::GetSealingMassMenuCommand",
                    "inventory::GetShovelMenuCommand",
                    "inventory::GetWrenchMenuCommand",
                    "inventory::GetSubmersibleWaterPumpMenuCommand",
                    "inventory::GetTuerOffnungKofferMenuCommand",
                    "inventory::GetWaterVacMenuCommand",
                    "omp::EnterVehicleCommand",
                    "pms::TreatPersonCommand",
                    "wmp::ConnectHoseBetweenCommand",
                    "wmp::ConnectHoseFirstCommand",
                    "wmp::ConnectHoseFirstToInputCommand",
                    "wmp::CoolCommand",
                    "wmp::DecontaminatePersonCommand",
                    "wmp::DisconnectHoseBetweenCommand",
                    "wmp::DisconnectHoseCommand",
                    "wmp::ExtinguishCommand",
                    "wmp::GetNormalSuitCommand",
                    "wmp::GroundHydrantOffCommand",
                    "wmp::GuidePersonCommand",
                    "wmp::OpenLockedBuildingDoorCommand",
                    "wmp::SetWaterBasinCommand",
                    "wmp::SetWaterPumpCommand",
                    "wmp::SetWaterSwitchCommand",
                    "wmp::ShowFirefighterEquipmentGuiCommand",
                    "wmp::ShowPsaEquipmentGuiCommand",
                    "wmp::ShowPumpEquipmentGuiCommand",
                    "wmp::ShowUSEquipmentGuiCommand",
                    "wmp::StartPullPersonCommand",
                    "wmp::StopGuidePersonCommand",
                    "wmp::StopPullPersonCommand",
                    "wmp::WaterBasinOffCommand",
                    "wmp::WaterPumpOffCommand",
                    "wmp::WaterSwitchOffCommand"
                ],
                "UnitType": "-1",
                "PlayerId": "-1"
            },
            "qsf::ActionComponent": "",
            "em5::PersonComponent": {
                "Gender": "GENDER_MALE"
            },
            "em5::PersonPlacementComponent": "",
            "qsf::BulletBoxCollisionComponent": {
                "CollisionMask": "37",
                "CollisionFilterGroup": "20",
                "HalfExtents": "0.40000000596046448 1 0.30000001192092896"
            },
            "em5::FireReceiverComponent": "",
            "em5::HighlightComponent": "",
            "qsf::ai::StuckResolverComponent": {
                "SwitchDelay": "1000000",
                "RegardTrafficImpedimentsAsStuck": "true"
            },
            "qsf::GameLogicComponent": {
                "GameLogicArray": [
                    {
                        "LogicTypeId": "em5::FiremanLogic"
                    }
                ]
            },
            "wmp::SuperFireFightersComponent": {
                "Person Type": "PERSON_TYPE_ABC_FIREFIGHER",
                "Firefighting Helmet": "11993657227757438546",
                "Chainsaw Helmet": "10395567598485325394"
            },
            "qsf::LinkComponent": "",
            "pms::DoctorLogicComponent": "",
            "pth::UnitTypeSetterComponent": {
                "Unit Type": "FirefighterABC"
            },
            "wmp::ScbaComponent": {
                "MaxVolume": "1200",
                "AirConsumptionIdle": "1",
                "AirConsumptionWalk": "1.5",
                "AirConsumptionWork": "2",
                "BaseOrderInfo (Only Dekon)": "core_pro_sw"
            },
            "pth::PersonAnimationHelper": "",
            "qsf::compositing::SkinnableMeshComponent": {
                "Mesh": "12345759"
            },
            "inventory::PresetComponent": {
                "PersonPreset": "fm-sw-dekon"
            }
        },
        "10395567598485325394": {
            "qsf::MetadataComponent": {
                "Prefab": "18446744073709551615",
                "Name": "fm_saw_helmet000"
            },
            "qsf::TransformComponent": {
                "Position": "0 1.7209010124206543 0.011322021484375",
                "Rotation": "0.48943883180618286 -0.51034188270568848 -0.489439457654953 0.51034283638000488"
            },
            "qsf::LinkComponent": {
                "ParentId": "3537955314538595921",
                "LocalPosition": "0 1.7209010124206543 0.011322021484375",
                "LocalRotation": "0.48943883180618286 -0.51034188270568848 -0.489439457654953 0.51034283638000488"
            },
            "qsf::game::BoneLinkComponent": {
                "BoneName": "Bip01_Head",
                "LocalPosition": "0 0 0",
                "LocalRotation": "1 0 0 0"
            },
            "qsf::MeshComponent": {
                "Mesh": "27846"
            },
            "wmp::HideAtStartupComponent": ""
        },
        "11993657227757438546": {
            "qsf::MetadataComponent": {
                "Prefab": "18446744073709551615",
                "Name": "draeger_hps_7000"
            },
            "qsf::TransformComponent": {
                "Position": "0 1.7508747577667236 0.01007080078125",
                "Rotation": "0.48943883180618286 -0.51034188270568848 -0.489439457654953 0.51034283638000488"
            },
            "qsf::compositing::SkinnableMeshComponent": {
                "Mesh": "1395535846",
                "Materials": [
                    "2228269487"
                ]
            },
            "qsf::LinkComponent": {
                "ParentId": "3537955314538595921",
                "LocalPosition": "0 1.7508747577667236 0.01007080078125",
                "LocalRotation": "0.48943883180618286 -0.51034188270568848 -0.489439457654953 0.51034283638000488"
            },
            "qsf::game::BoneLinkComponent": {
                "BoneName": "Bip01_Head",
                "LocalPosition": "0.029999999329447746 0 0",
                "LocalRotation": "1 0 0 0"
            }
        },
        "15314086471380977234": {
            "qsf::MetadataComponent": {
                "Prefab": "18446744073709551615",
                "Name": "facemask000"
            },
            "qsf::TransformComponent": {
                "Position": "0 1.6852507591247559 -0.07525634765625",
                "Rotation": "0.99978148937225342 -0.020903214812278748 1.7881393432617188e-07 7.8976154327392578e-07"
            },
            "qsf::MeshComponent": {
                "Mesh": "1395537831"
            },
            "qsf::LinkComponent": {
                "ParentId": "3537955314538595921",
                "LocalPosition": "0 1.6852507591247559 -0.07525634765625",
                "LocalRotation": "0.99978148937225342 -0.020903214812278748 1.7881393432617188e-07 7.8976154327392578e-07"
            },
            "qsf::game::BoneLinkComponent": {
                "BoneName": "Bip01_Head",
                "LocalPosition": "-0.032000001519918442 0.087999999523162842 0",
                "LocalRotation": "0.5 0.5 0.5 -0.5"
            }
        }
    }
}
