{
    "Format": {
        "Type": "prefab",
        "Version": "2",
        "DifferenceToDefault": "true"
    },
    "Prototypes": {
        "12722139601629218365": {
            "qsf::MetadataComponent": {
                "Prefab": "18446744073709551615",
                "Name": "core_at3_gr",
                "Description": "gr"
            },
            "qsf::TransformComponent": "",
            "qsf::compositing::SkinnableMeshComponent": {
                "InheritTintColor": "true",
                "Mesh": "4108",
                "Materials": [
                    "4504"
                ]
            },
            "qsf::LinkComponent": {
                "LocalPosition": "0.0192413330078125 2.6873471736907959 4.1451416015625",
                "LocalRotation": "-5.9604644775390625e-08 0.70710670948028564 -1.0430814256778831e-07 -0.70710688829421997"
            },
            "em5::DoorComponent": {
                "OpeningAnimation": "18446744073709551615",
                "ClosingAnimation": "18446744073709551615",
                "CuttingAnimation": "18446744073709551615",
                "RotationAxis": "0 0 1",
                "RotationAngle": "85",
                "OpeningAnimationLength": "1000000",
                "ClosingAnimationLength": "1000000"
            }
        },
        "17992156171372987965": {
            "qsf::MetadataComponent": {
                "Prefab": "18446744073709551615",
                "Name": "kfz_kennzeichen_euro_1000"
            },
            "qsf::TransformComponent": {
                "Position": "0.038635320961475372 1.1920429468154907 0.011657420545816422"
            },
            "qsf::compositing::SkinnableMeshComponent": {
                "Mesh": "1395528439"
            },
            "qsf::LinkComponent": {
                "ParentId": "12722139601629218365",
                "LocalPosition": "0.038635320961475372 1.1920429468154907 0.011657420545816422",
                "LocalRotation": "-5.9604644775390625e-08 -0.70710670948028564 1.0430814256778831e-07 0.70710688829421997"
            }
        },
        "8709468754964776510": {
            "qsf::MetadataComponent": {
                "Prefab": "18446744073709551615",
                "Name": "debug_box000",
                "Description": "Debug box with the dimension 1x1x1 meter",
                "Tags": "debug"
            },
            "qsf::DebugBoxComponent": {
                "Color": "0.75 0.75 0.75 1",
                "ShowDirection": "true",
                "CenterAtPivot": "true",
                "RenderQueueId": "90"
            },
            "qsf::TransformComponent": {
                "Position": "0.035091526806354523 1.1825212240219116 0.19850128889083862",
                "Rotation": "0.49999994039535522 -0.5 0.50000017881393433 0.50000005960464478"
            },
            "pth::LicensePlateComponent": {
                "Plate Type": "TYPE_CAR",
                "City": "DR",
                "Combination": "25915",
                "HU Plate": "HU_PLATE_NONE",
                "HU Termination": "DATE_JUNE",
                "State": "STATE_NONE",
                "Chars": [
                    "8990145434694059582",
                    "17042091169066649152",
                    "18112079719930922559",
                    "6663644882622088767",
                    "16375545285910857280",
                    "3263474335583176255",
                    "9249976447702533694"
                ]
            },
            "qsf::LinkComponent": {
                "ParentId": "17992156171372987965",
                "LocalPosition": "-0.18684385716915131 0.0095218103379011154 0.003543853759765625",
                "LocalRotation": "0.7071068286895752 0.7071068286895752 2.0097183127203676e-14 5.6843418860808015e-14"
            }
        },
        "3263474335583176255": {
            "qsf::MetadataComponent": {
                "Prefab": "18446744073709551615",
                "Name": "fe_font000"
            },
            "qsf::MeshComponent": {
                "CastShadows": "false",
                "RenderingDistanceFactor": "2",
                "Mesh": "1395535735"
            },
            "qsf::TransformComponent": {
                "Position": "0.035091377794742584 1.1825211048126221 -0.13649877905845642",
                "Rotation": "0.49999994039535522 -0.5 0.50000017881393433 0.50000005960464478"
            },
            "qsf::LinkComponent": {
                "ParentId": "8709468754964776510",
                "LocalPosition": "0.33500000834465027 0 0"
            },
            "pth::UvOffsetComponent": {
                "U Offset": "0.111328125",
                "V Offset": "0.72265625"
            }
        },
        "6663644882622088767": {
            "qsf::MetadataComponent": {
                "Prefab": "18446744073709551615",
                "Name": "fe_font000"
            },
            "qsf::MeshComponent": {
                "CastShadows": "false",
                "RenderingDistanceFactor": "2",
                "Mesh": "1395535735"
            },
            "qsf::TransformComponent": {
                "Position": "0.035091407597064972 1.1825212240219116 -0.036498755216598511",
                "Rotation": "0.49999994039535522 -0.5 0.50000017881393433 0.50000005960464478"
            },
            "qsf::LinkComponent": {
                "ParentId": "8709468754964776510",
                "LocalPosition": "0.23499999940395355 0 0"
            },
            "pth::UvOffsetComponent": {
                "U Offset": "0.55078125",
                "V Offset": "0.72265625"
            }
        },
        "8990145434694059582": {
            "qsf::MetadataComponent": {
                "Prefab": "18446744073709551615",
                "Name": "fe_font000"
            },
            "qsf::MeshComponent": {
                "CastShadows": "false",
                "RenderingDistanceFactor": "2",
                "Mesh": "1395535735"
            },
            "qsf::TransformComponent": {
                "Position": "0.035091511905193329 1.1825212240219116 0.16350129246711731",
                "Rotation": "0.49999994039535522 -0.5 0.50000017881393433 0.50000005960464478"
            },
            "qsf::LinkComponent": {
                "ParentId": "8709468754964776510",
                "LocalPosition": "0.035000000149011612 0 0"
            },
            "pth::UvOffsetComponent": {
                "U Offset": "0.33203125",
                "V Offset": "0.001953125"
            }
        },
        "9249976447702533694": {
            "qsf::MetadataComponent": {
                "Prefab": "18446744073709551615",
                "Name": "fe_font000"
            },
            "qsf::MeshComponent": {
                "CastShadows": "false",
                "RenderingDistanceFactor": "2",
                "Mesh": "1395535735"
            },
            "qsf::TransformComponent": {
                "Position": "0.035091318190097809 1.1825211048126221 -0.18649876117706299",
                "Rotation": "0.49999994039535522 -0.5 0.50000017881393433 0.50000005960464478"
            },
            "qsf::LinkComponent": {
                "ParentId": "8709468754964776510",
                "LocalPosition": "0.38499999046325684 0 0"
            },
            "pth::UvOffsetComponent": {
                "U Offset": "0.55078125",
                "V Offset": "0.72265625"
            }
        },
        "16375545285910857280": {
            "qsf::MetadataComponent": {
                "Prefab": "18446744073709551615",
                "Name": "fe_font000"
            },
            "qsf::MeshComponent": {
                "CastShadows": "false",
                "RenderingDistanceFactor": "2",
                "Mesh": "1395535735"
            },
            "qsf::TransformComponent": {
                "Position": "0.035091407597064972 1.1825212240219116 -0.086498737335205078",
                "Rotation": "0.49999994039535522 -0.5 0.50000017881393433 0.50000005960464478"
            },
            "qsf::LinkComponent": {
                "ParentId": "8709468754964776510",
                "LocalPosition": "0.28499999642372131 0 0"
            },
            "pth::UvOffsetComponent": {
                "U Offset": "0.001953125",
                "V Offset": "0.84375"
            }
        },
        "17042091169066649152": {
            "qsf::MetadataComponent": {
                "Prefab": "18446744073709551615",
                "Name": "fe_font000"
            },
            "qsf::MeshComponent": {
                "CastShadows": "false",
                "RenderingDistanceFactor": "2",
                "Mesh": "1395535735"
            },
            "qsf::TransformComponent": {
                "Position": "0.035091489553451538 1.1825212240219116 0.11350127309560776",
                "Rotation": "0.49999994039535522 -0.5 0.50000017881393433 0.50000005960464478"
            },
            "qsf::LinkComponent": {
                "ParentId": "8709468754964776510",
                "LocalPosition": "0.085000000894069672 0 0"
            },
            "pth::UvOffsetComponent": {
                "U Offset": "0.880859375",
                "V Offset": "0.12109375"
            }
        },
        "18112079719930922559": {
            "qsf::MetadataComponent": {
                "Prefab": "18446744073709551615",
                "Name": "fe_font000"
            },
            "qsf::MeshComponent": {
                "CastShadows": "false",
                "RenderingDistanceFactor": "2",
                "Mesh": "1395535735"
            },
            "qsf::TransformComponent": {
                "Position": "0.035091452300548553 1.1825212240219116 0.013501256704330444",
                "Rotation": "0.49999994039535522 -0.5 0.50000017881393433 0.50000005960464478"
            },
            "qsf::LinkComponent": {
                "ParentId": "8709468754964776510",
                "LocalPosition": "0.18500000238418579 0 0"
            },
            "pth::UvOffsetComponent": {
                "U Offset": "0.220703125",
                "V Offset": "0.72265625"
            }
        }
    }
}
